tensorflow_serving/__init__.py
tensorflow_serving/apis/__init__.py
tensorflow_serving/apis/classification_pb2.py
tensorflow_serving/apis/get_model_metadata_pb2.py
tensorflow_serving/apis/inference_pb2.py
tensorflow_serving/apis/input_pb2.py
tensorflow_serving/apis/model_pb2.py
tensorflow_serving/apis/model_service_pb2.py
tensorflow_serving/apis/model_service_pb2_grpc.py
tensorflow_serving/apis/predict_pb2.py
tensorflow_serving/apis/prediction_service_pb2.py
tensorflow_serving/apis/regression_pb2.py
tensorflow_serving_api_python3-1.8.0.dist-info/METADATA
tensorflow_serving_api_python3-1.8.0.dist-info/RECORD
tensorflow_serving_api_python3-1.8.0.dist-info/WHEEL
tensorflow_serving_api_python3-1.8.0.dist-info/top_level.txt
tensorflow_serving_api_python3-1.8.0.dist-info/zip-safe
