Metadata-Version: 2.1
Name: tensorflow-serving-api-python3
Version: 1.8.0
Summary: *UNOFFICIAL* TensorFlow Serving API libraries for Python3
Home-page: https://github.com/illagrenan/tensorflow-serving-api-python3
Author: Vašek Dohnal
Author-email: tensorflow-serving-dev@googlegroups.com
License: Apache 2.0
Keywords: TensorFlow Serving API libraries
Platform: UNKNOWN
Classifier: Development Status :: 3 - Alpha
Classifier: Intended Audience :: Developers
Classifier: Natural Language :: English
Classifier: Programming Language :: Python :: 3.5
Classifier: Programming Language :: Python :: 3.6
Classifier: Programming Language :: Python :: 3 :: Only
Classifier: Operating System :: OS Independent
Requires-Python: ~=3.5
Requires-Dist: grpcio (>=1.7.0)
Requires-Dist: tensorflow (>=1.8.0)
